iron_core.py
iron_core-1.2.1.dist-info/LICENSE.txt
iron_core-1.2.1.dist-info/METADATA
iron_core-1.2.1.dist-info/WHEEL
iron_core-1.2.1.dist-info/top_level.txt
iron_core-1.2.1.dist-info/RECORD
